odoo/addons/web_dashboard_tile/README.rst
odoo/addons/web_dashboard_tile/__init__.py
odoo/addons/web_dashboard_tile/__manifest__.py
odoo/addons/web_dashboard_tile/controllers/__init__.py
odoo/addons/web_dashboard_tile/controllers/main.py
odoo/addons/web_dashboard_tile/demo/tile_category.xml
odoo/addons/web_dashboard_tile/demo/tile_tile.xml
odoo/addons/web_dashboard_tile/i18n/fr.po
odoo/addons/web_dashboard_tile/i18n/web_dashboard_tile.pot
odoo/addons/web_dashboard_tile/migrations/12.0.1.0.0/post-migration.py
odoo/addons/web_dashboard_tile/models/__init__.py
odoo/addons/web_dashboard_tile/models/tile_category.py
odoo/addons/web_dashboard_tile/models/tile_tile.py
odoo/addons/web_dashboard_tile/readme/CONFIGURE.rst
odoo/addons/web_dashboard_tile/readme/CONTRIBUTORS.rst
odoo/addons/web_dashboard_tile/readme/DESCRIPTION.rst
odoo/addons/web_dashboard_tile/readme/ROADMAP.rst
odoo/addons/web_dashboard_tile/readme/USAGE.rst
odoo/addons/web_dashboard_tile/security/ir.model.access.csv
odoo/addons/web_dashboard_tile/security/ir_rule.xml
odoo/addons/web_dashboard_tile/static/description/favorite_menu_create_tile.png
odoo/addons/web_dashboard_tile/static/description/favorite_menu_create_tile_result.png
odoo/addons/web_dashboard_tile/static/description/icon.png
odoo/addons/web_dashboard_tile/static/description/index.html
odoo/addons/web_dashboard_tile/static/description/tile_category_form.png
odoo/addons/web_dashboard_tile/static/description/tile_tile_2_tree_view.png
odoo/addons/web_dashboard_tile/static/description/tile_tile_form.png
odoo/addons/web_dashboard_tile/static/description/tile_tile_form_secondary_value.png
odoo/addons/web_dashboard_tile/static/description/tile_tile_kanban.png
odoo/addons/web_dashboard_tile/static/src/css/web_dashboard_tile.css
odoo/addons/web_dashboard_tile/tests/__init__.py
odoo/addons/web_dashboard_tile/tests/test_tile.py
odoo/addons/web_dashboard_tile/views/menu.xml
odoo/addons/web_dashboard_tile/views/templates.xml
odoo12_addon_web_dashboard_tile-12.0.1.0.2.dist-info/METADATA
odoo12_addon_web_dashboard_tile-12.0.1.0.2.dist-info/WHEEL
odoo12_addon_web_dashboard_tile-12.0.1.0.2.dist-info/top_level.txt
odoo12_addon_web_dashboard_tile-12.0.1.0.2.dist-info/RECORD
