Metadata-Version: 2.1
Name: odoo12-addon-web-dashboard-tile
Version: 12.0.1.0.2
Summary: Add Overview Dashboards with Tiles
Home-page: https://github.com/OCA/web
Author: initOS GmbH & Co. KG, GRAP, Iván Todorovich <ivan.todorovich@gmail.com>, Odoo Community Association (OCA)
Author-email: support@odoo-community.org
License: AGPL-3
Platform: UNKNOWN
Classifier: Programming Language :: Python
Classifier: Framework :: Odoo
Classifier: Framework :: Odoo :: 12.0
Classifier: License :: OSI Approved :: GNU Affero General Public License v3
Requires-Python: >=3.5
Requires-Dist: odoo12-addon-web-widget-color
Requires-Dist: odoo (<12.1dev,>=12.0a)
